{
    "id": 119259720,
    "verification": "https://youtube.com/embed/b1nXdQNGucc",
    "records": [
        {
            "user": "foin",
            "link": "https://youtu.be/b1nXdQNGucc?si=8jQnyWHKt5pK7nzM",
            "percent": 100
        },
        {
            "user": "Noxical",
            "link": "https://youtu.be/TNlTtKNYdAg?si=esNlvWQr295Qf0iO",
            "percent": 100
        },
        {
            "user": "dofar",
            "link": "https://www.youtube.com/watch?v=RhcpvUTroSU",
            "percent": 100
        },
        {
            "user": "dubo",
            "link": "https://th.bing.com/th/id/OIP.Z9X51f4mO99PkAl1N5yBhAHaHa?rs=1&pid=ImgDetMain",
            "percent": 88
        }
    ]
}